{"day": 94, "astronauts": [{"id": "a1", "name": "Alex", "bodyMassKg": 75.0, "dailyCalorieNeed": 3000.0, "dailyProteinNeedG": 112.5, "dailyWaterNeedL": 2.3, "carbTargetPct": 0.5, "proteinTargetPct": 0.175, "fatTargetPct": 0.325, "vitaminA_ug": 900.0, "vitaminC_mg": 90.0, "vitaminK_ug": 120.0, "folate_ug": 400.0, "potassium_mg": 4700.0, "calorieDeficitAccumulated": 93000.0, "proteinDeficitAccumulated": 3487.5, "hydrationLevel": 1.0, "micronutrientScore": 0.009393946474176, "cognitivePerformance": 0.0037575785896704003, "boneHealthScore": 0.8179999999999998, "immuneScore": 0.06255007261813629, "isAlive": false, "storedFoodCalories": 0.0, "storedFoodProteinG": 0.0}, {"id": "a2", "name": "Jordan", "bodyMassKg": 75.0, "dailyCalorieNeed": 3000.0, "dailyProteinNeedG": 112.5, "dailyWaterNeedL": 2.3, "carbTargetPct": 0.5, "proteinTargetPct": 0.175, "fatTargetPct": 0.325, "vitaminA_ug": 900.0, "vitaminC_mg": 90.0, "vitaminK_ug": 120.0, "folate_ug": 400.0, "potassium_mg": 4700.0, "calorieDeficitAccumulated": 93000.0, "proteinDeficitAccumulated": 3487.5, "hydrationLevel": 1.0, "micronutrientScore": 0.009393946474176, "cognitivePerformance": 0.0037575785896704003, "boneHealthScore": 0.8179999999999998, "immuneScore": 0.06255007261813629, "isAlive": false, "storedFoodCalories": 0.0, "storedFoodProteinG": 0.0}, {"id": "a3", "name": "Sam", "bodyMassKg": 75.0, "dailyCalorieNeed": 3000.0, "dailyProteinNeedG": 112.5, "dailyWaterNeedL": 2.3, "carbTargetPct": 0.5, "proteinTargetPct": 0.175, "fatTargetPct": 0.325, "vitaminA_ug": 900.0, "vitaminC_mg": 90.0, "vitaminK_ug": 120.0, "folate_ug": 400.0, "potassium_mg": 4700.0, "calorieDeficitAccumulated": 93000.0, "proteinDeficitAccumulated": 3487.5, "hydrationLevel": 1.0, "micronutrientScore": 0.009393946474176, "cognitivePerformance": 0.0037575785896704003, "boneHealthScore": 0.8179999999999998, "immuneScore": 0.06255007261813629, "isAlive": false, "storedFoodCalories": 0.0, "storedFoodProteinG": 0.0}, {"id": "a4", "name": "Riley", "bodyMassKg": 75.0, "dailyCalorieNeed": 3000.0, "dailyProteinNeedG": 112.5, "dailyWaterNeedL": 2.3, "carbTargetPct": 0.5, "proteinTargetPct": 0.175, "fatTargetPct": 0.325, "vitaminA_ug": 900.0, "vitaminC_mg": 90.0, "vitaminK_ug": 120.0, "folate_ug": 400.0, "potassium_mg": 4700.0, "calorieDeficitAccumulated": 93000.0, "proteinDeficitAccumulated": 3487.5, "hydrationLevel": 1.0, "micronutrientScore": 0.009393946474176, "cognitivePerformance": 0.0037575785896704003, "boneHealthScore": 0.8179999999999998, "immuneScore": 0.06255007261813629, "isAlive": false, "storedFoodCalories": 0.0, "storedFoodProteinG": 0.0}], "plants": [{"name": "Potato", "count": 10, "hydration": 0.0, "days_planted": 94, "growth_cycle_days": 90, "area_m2": 5.0}, {"name": "Lettuce", "count": 15, "hydration": 0.0, "days_planted": 94, "growth_cycle_days": 35, "area_m2": 4.0}, {"name": "Radish", "count": 20, "hydration": 0.0, "days_planted": 94, "growth_cycle_days": 25, "area_m2": 3.0}, {"name": "Beans", "count": 8, "hydration": 0.0, "days_planted": 94, "growth_cycle_days": 60, "area_m2": 3.0}, {"name": "Herbs", "count": 5, "hydration": 0.0, "days_planted": 94, "growth_cycle_days": 30, "area_m2": 1.0}], "resources": {"water_liters": 162.8000000000079, "growing_area_m2": 50.0, "energy_kwh": 500.0}, "inventory": {"Potato": 0.0, "Lettuce": 0.0, "Radish": 0.0, "Beans": 0.0, "Herbs": 0.0}}